MANIFEST.in
setup.py
legofy/__init__.py
legofy/cli.py
legofy/images2gif_py2.py
legofy/images2gif_py3.py
legofy/legofy_gui.py
legofy/palettes.py
legofy.egg-info/PKG-INFO
legofy.egg-info/SOURCES.txt
legofy.egg-info/dependency_links.txt
legofy.egg-info/entry_points.txt
legofy.egg-info/requires.txt
legofy.egg-info/top_level.txt
legofy/assets/bricks/1x1.png