Metadata-Version: 1.1
Name: legofy
Version: 1.0.0
Summary: Make images look as if they are made out of 1x1 LEGO blocks
Home-page: https://github.com/JuanPotato/Legofy
Author: Juan Potato
Author-email: juanpotatodev@gmail.com
License: MIT
Platform: UNKNOWN
Classifier: Development Status :: 4 - Beta
Classifier: Programming Language :: Python
